candle_driver.cp39-win_amd64.pyd
candle_driver-0.1.5.dist-info/LICENSE
candle_driver-0.1.5.dist-info/METADATA
candle_driver-0.1.5.dist-info/WHEEL
candle_driver-0.1.5.dist-info/top_level.txt
candle_driver-0.1.5.dist-info/RECORD
