Metadata-Version: 2.1
Name: candle-driver
Version: 0.1.5
Summary: Python wrapper for the candle (gs_usb) windows driver.
Home-page: https://github.com/chemicstry/candle_driver
Author: Jurgis Balčiūnas
Author-email: chemicstry@gmail.com
License: MIT
Platform: UNKNOWN
Requires-Python: >=3.6.0
